[
  {
    "course": "ÖTILLÖ Swimrun Cannes — 22 juin 2025",
    "nom": "Thierry",
    "prenom": "KENNES",
    "email": "thierry@email.com",
    "telephone": "87 12 34 56",
    "commentaire": "je vais pour le fun, je suis pas très compétitif",
    "date": "2026-06-13",
    "id": "1781395049292"
  },
  {
    "course": "Swimrun de Bretagne — 6 septembre 2025",
    "nom": "Mamie",
    "prenom": "Bretagne",
    "email": "mamie@email.com",
    "telephone": "87 11 11111",
    "commentaire": "Objectif TOP 10, je cours à 3min/km et je cherche un·e binôme sérieux·se 💪",
    "date": "2026-06-13",
    "id": "1781395090419"
  }
]